MANIFEST.in
README.md
setup.cfg
setup.py
secp256k1py/__init__.py
secp256k1py/curv.c
secp256k1py/curv.pyx
secp256k1py/functions.py
secp256k1py/secp256k1.py
secp256k1py.egg-info/PKG-INFO
secp256k1py.egg-info/SOURCES.txt
secp256k1py.egg-info/dependency_links.txt
secp256k1py.egg-info/entry_points.txt
secp256k1py.egg-info/requires.txt
secp256k1py.egg-info/top_level.txt
secp256k1py.egg-info/zip-safe