Metadata-Version: 1.0
Name: secp256k1py
Version: 0.1.11
Summary: Python version secp256k1 keypair generator signature and verify, ecdh secret sharing, for human mind
Home-page: https://github.com/ipconfiger/secp256k1-py
Author: Alexander.Li
Author-email: superpowerlee@gmail.com
License: MIT
Keywords: ecc,ecdh,secp256k1,signature,verification
Platform: UNKNOWN
